{"application" : "color_detect_v1_1080p",
    "kernels": {
        "threshold1": {
            "name": "threshold1_0",
            "type": "CT",
            "ktype": "threshold1",
            "tloc": [0, 3],
            "ports": {
                "thresholdValue1u": {
                    "name": "thresholdValue1u",
                    "dtype": "int16_t",
                    "ctype": "rtp",
                    "value": 190,
                    "c_dtype": "int16_t"
                },
                "thresholdValue1l": {
                    "name": "thresholdValue1l",
                    "dtype": "int16_t",
                    "ctype": "rtp",
                    "value": 150,
                    "c_dtype": "int16_t"
                }
            }
        },
        "threshold2": {
            "name": "threshold2_0",
            "type": "CT",
            "ktype": "threshold2",
            "tloc": [0, 4],
            "ports": {
                "thresholdValue2u": {
                    "name": "thresholdValue2u",
                    "dtype": "int16_t",
                    "ctype": "rtp",
                    "value": 255,
                    "c_dtype": "int16_t"
                },
                "thresholdValue2l": {
                    "name": "thresholdValue2l",
                    "dtype": "int16_t",
                    "ctype": "rtp",
                    "value": 230,
                    "c_dtype": "int16_t"
                }
            }
        }
    }
}
